pytest_lark/__init__.py
pytest_lark/conftest.py
pytest_lark/lark.py
pytest_lark/list_files.py
pytest_lark/pytest_reports.py
pytest_lark/source.py
pytest_lark-0.2.1.dist-info/LICENSE
pytest_lark-0.2.1.dist-info/METADATA
pytest_lark-0.2.1.dist-info/WHEEL
pytest_lark-0.2.1.dist-info/top_level.txt
pytest_lark-0.2.1.dist-info/RECORD
