Metadata-Version: 2.1
Name: pytest-lark
Version: 0.2.1
Summary: Create fancy and clear HTML test reports.
Author-email: Mark Hoo <markhoo@foxmail.com>
Project-URL: Homepage, https://github.com/MarkHoo/pytest-lark
Project-URL: Bug Tracker, https://github.com/MarkHoo/pytest-lark/issues
Classifier: Programming Language :: Python :: 3
Classifier: License :: OSI Approved :: Apache Software License
Classifier: Operating System :: OS Independent
Classifier: Framework :: Pytest
Classifier: Programming Language :: Python :: 3.8
Classifier: Programming Language :: Python :: 3.9
Classifier: Programming Language :: Python :: 3.10
Classifier: Programming Language :: Python :: 3.11
Classifier: Programming Language :: Python :: 3.12
Requires-Python: >=3.8
License-File: LICENSE
